README
setup.py
lib/pexpect.py
lib/winpexpect.py
lib/winpexpect.egg-info/PKG-INFO
lib/winpexpect.egg-info/SOURCES.txt
lib/winpexpect.egg-info/dependency_links.txt
lib/winpexpect.egg-info/not-zip-safe
lib/winpexpect.egg-info/requires.txt
lib/winpexpect.egg-info/top_level.txt