Metadata-Version: 1.0
Name: winpexpect
Version: 1.4
Summary: A version of pexpect that works under Windows.
Home-page: http://bitbucket.org/geertj/winpexpect
Author: Geert Jansen
Author-email: geert@boskant.nl
License: MIT
Platform: UNKNOWN
Classifier: Development Status :: 4 - Beta
Classifier: Intended Audience :: Developers
Classifier: License :: OSI Approved :: MIT License
Classifier: Programming Language :: Python
Classifier: Operating System :: Microsoft :: Windows
